skymakercam/__init__.py
skymakercam/__main__.py
skymakercam/camera.py
skymakercam/catalog.py
skymakercam/coords.py
skymakercam/etc/cameras.yaml
skymakercam/etc/skymakercam.yml
skymakercam/exceptions.py
skymakercam/params/__init__.py
skymakercam/params/lvm_agc_cam.py
skymakercam/params/lvm_age_cam.py
skymakercam/params/lvm_agw_cam.py
skymakercam/params/lvm_common.py
skymakercam/params/lvm_ifu_positions.py
skymakercam/starimage.py
sdss_skymakercam-0.0.30.dist-info/LICENSE.md
sdss_skymakercam-0.0.30.dist-info/METADATA
sdss_skymakercam-0.0.30.dist-info/WHEEL
sdss_skymakercam-0.0.30.dist-info/entry_points.txt
sdss_skymakercam-0.0.30.dist-info/RECORD
