Metadata-Version: 2.1
Name: sdss-skymakercam
Version: 0.0.30
Summary: Skymaker camera with sdss-basecam
Home-page: https://github.com/sdss/skymakercam
License: BSD-3-Clause
Keywords: astronomy,software
Author: Florian Briegel
Author-email: briegel@mpia.de
Requires-Python: >=3.8,<=3.10
Classifier: Intended Audience :: Science/Research
Classifier: License :: OSI Approved :: BSD License
Classifier: Natural Language :: English
Classifier: Operating System :: OS Independent
Classifier: Programming Language :: Python :: 3
Classifier: Programming Language :: Python :: 3.8
Classifier: Programming Language :: Python :: 3.9
Classifier: Programming Language :: Python :: 3.10
Classifier: Programming Language :: Python :: 3.10
Classifier: Programming Language :: Python :: 3.8
Classifier: Programming Language :: Python :: 3.9
Classifier: Topic :: Documentation :: Sphinx
Classifier: Topic :: Software Development :: Libraries :: Python Modules
Requires-Dist: PyQt5 (>=5.14)
Requires-Dist: astropy (>=5.2)
Requires-Dist: astroquery (>0.4)
Requires-Dist: asyncudp (>=0.4)
Requires-Dist: click-default-group (>=1.2.2,<2.0.0)
Requires-Dist: healpy (>=1.15)
Requires-Dist: jsonpickle (==1.3)
Requires-Dist: keyboard (>0.13)
Requires-Dist: matplotlib (>=3.1.1)
Requires-Dist: numpy (>=1.0)
Requires-Dist: scikit_image (>=0.18)
Requires-Dist: scipy (>=1.7)
Requires-Dist: sdss-basecam (>=0.5)
Requires-Dist: sdss-cluplus (>=0.2.1)
Requires-Dist: sdss-lvmtipo (>=0.0.7)
Requires-Dist: sdsstools (>=0.4.0)
Requires-Dist: sep (>=1.2)
Requires-Dist: transitions (>0.8)
Project-URL: Documentation, https://sdss-skymakercam.readthedocs.org
Project-URL: Repository, https://github.com/sdss/skymakercam
